score/jinja2/__init__.py
score/jinja2/_init.py
score.jinja2-0.1.1.dist-info/METADATA
score.jinja2-0.1.1.dist-info/WHEEL
score.jinja2-0.1.1.dist-info/top_level.txt
score.jinja2-0.1.1.dist-info/RECORD
