Metadata-Version: 2.1
Name: score.jinja2
Version: 0.1.1
Home-page: http://score-framework.org
Author: strg.at
Author-email: score@strg.at
License: LGPL
Keywords: score framework template jinja2
Requires-Dist: score.init
Requires-Dist: score.tpl (>=0.3.0)
Requires-Dist: jinja2 (<3.0)
